CHANGES.txt
LICENSE
MANIFEST.in
README.txt
pyproject.toml
vul_ok.txt
bid/inventory.servers
bid/inventoryClient.py
bid/inventoryServer.py
bid/monitorClient.py
contrib/soap_cli.py
contrib/soap_handler.py
docs/GettingStarted.txt
docs/GlobusSupport.txt
docs/MethodParameterNaming.txt
docs/UsingHeaders.txt
docs/WSDL.txt
docs/attrs.txt
docs/complexTypes.txt
docs/simpleTypes.txt
src/SOAPpy/Client.py
src/SOAPpy/Config.py
src/SOAPpy/Errors.py
src/SOAPpy/GSIServer.py
src/SOAPpy/NS.py
src/SOAPpy/Parser.py
src/SOAPpy/SOAP.py
src/SOAPpy/SOAPBuilder.py
src/SOAPpy/Server.py
src/SOAPpy/TwistedSOAPProxy.py
src/SOAPpy/TwistedSOAPPublisher.py
src/SOAPpy/Types.py
src/SOAPpy/URLopener.py
src/SOAPpy/Utilities.py
src/SOAPpy/WSDL.py
src/SOAPpy/__init__.py
src/SOAPpy/version.py
src/SOAPpy_py3.egg-info/PKG-INFO
src/SOAPpy_py3.egg-info/SOURCES.txt
src/SOAPpy_py3.egg-info/dependency_links.txt
src/SOAPpy_py3.egg-info/requires.txt
src/SOAPpy_py3.egg-info/top_level.txt
tests/BabelfishWSDLTest.py
tests/Bug1001646.py
tests/Bug916265.py
tests/Bug918216.py
tests/ComplexTypes.py
tests/GoogleTest.py
tests/SOAPtest.py
tests/TCtest.py
tests/TemperatureService.wsdl
tests/ZeroLengthArray.py
tests/alanbushTest.py
tests/cardClient.py
tests/cardServer.py
tests/echoClient.py
tests/echoHeader.py
tests/echoServer.py
tests/esj_test_client.py
tests/esj_test_server.py
tests/excelTest.py
tests/largeDataTest.py
tests/newsTest.py
tests/quoteTest.py
tests/simpleWSDL.py
tests/speedTest.py
tests/storageTest.py
tests/testClient1.py
tests/testWSDL.py
tests/testleak.py
tests/testsclient.py
tests/testserver.py
tests/translateTest.py
tests/vul_etcpasswd.txt
tests/vul_lol.txt
tests/weatherTest.py
tests/whoisTest.py
tests/xmethods.py
tools/interop2html.py
validate/server.pem
validate/silab.servers
validate/silabclient.py
validate/silabserver.py
validate/soapware.py
zope/README
zope/zope-2.5.0-soappy.diff
zope/zope-2.6.2-soappy.diff
zope/zope-soap-client.py