Metadata-Version: 2.1
Name: SOAPpy-py3
Version: 0.52.30
Summary: SOAP Services for Python
Maintainer-email: Synerty <contact@synerty.com>
Project-URL: Homepage, https://github.com/Synerty/SOAPpy-py3
Classifier: Programming Language :: Python
Classifier: Programming Language :: Python :: 3
Classifier: Development Status :: 5 - Production/Stable
Classifier: Environment :: Other Environment
Classifier: Intended Audience :: Developers
Classifier: Operating System :: OS Independent
Classifier: Topic :: Software Development :: Libraries :: Python Modules
Classifier: Programming Language :: Python :: 3.4
Classifier: Programming Language :: Python :: 3.5
Classifier: Topic :: Internet :: WWW/HTTP
Provides: SOAPpy
License-File: LICENSE
Requires-Dist: wstools-py3
Requires-Dist: defusedxml
